__init__.py
isodd.py
new_is_odd-0.0.1.dist-info/LICENSE
new_is_odd-0.0.1.dist-info/METADATA
new_is_odd-0.0.1.dist-info/WHEEL
new_is_odd-0.0.1.dist-info/top_level.txt
new_is_odd-0.0.1.dist-info/RECORD
